.testr.conf
AUTHORS
CONTRIBUTING.rst
ChangeLog
HACKING.rst
LICENSE
README.rst
openstack-common.conf
requirements.txt
run_tests.sh
setup.cfg
setup.py
test-requirements.txt
tox.ini
doc/source/conf.py
doc/source/index.rst
evoqueclient/__init__.py
evoqueclient/client.py
evoqueclient/shell.py
evoqueclient/version.py
evoqueclient/common/__init__.py
evoqueclient/common/base.py
evoqueclient/common/exceptions.py
evoqueclient/common/http.py
evoqueclient/common/utils.py
evoqueclient/openstack/__init__.py
evoqueclient/openstack/common/__init__.py
evoqueclient/openstack/common/gettextutils.py
evoqueclient/openstack/common/apiclient/__init__.py
evoqueclient/openstack/common/apiclient/exceptions.py
evoqueclient/tests/__init__.py
evoqueclient/tests/test_common.py
evoqueclient/v1/__init__.py
evoqueclient/v1/client.py
evoqueclient/v1/shell.py
evoqueclient/v1/tickets.py
python_evoqueclient.egg-info/PKG-INFO
python_evoqueclient.egg-info/SOURCES.txt
python_evoqueclient.egg-info/dependency_links.txt
python_evoqueclient.egg-info/entry_points.txt
python_evoqueclient.egg-info/not-zip-safe
python_evoqueclient.egg-info/pbr.json
python_evoqueclient.egg-info/requires.txt
python_evoqueclient.egg-info/top_level.txt
tools/evoque.bash_completion
tools/install_venv.py
tools/install_venv_common.py
tools/with_venv.sh